hiargparse/__init__.py
hiargparse/_version.py
hiargparse/alternatives/__init__.py
hiargparse/alternatives/arg_parse.py
hiargparse/alternatives/namespace.py
hiargparse/args_providers/__init__.py
hiargparse/args_providers/args_provider.py
hiargparse/args_providers/argument.py
hiargparse/args_providers/child_provider.py
hiargparse/args_providers/exceptions.py
hiargparse/file_protocols/__init__.py
hiargparse/file_protocols/configure_file_type.py
hiargparse/file_protocols/dict_readers/__init__.py
hiargparse/file_protocols/dict_readers/abstract_dict_reader.py
hiargparse/file_protocols/dict_readers/added_double_hyphen.py
hiargparse/file_protocols/dict_readers/normalize_dict.py
hiargparse/file_protocols/dict_readers/toml_reader.py
hiargparse/file_protocols/dict_readers/yaml_reader.py
hiargparse/file_protocols/dict_writers/__init__.py
hiargparse/file_protocols/dict_writers/abstract_dict_writer.py
hiargparse/file_protocols/dict_writers/null_writer.py
hiargparse/file_protocols/dict_writers/raw_writer.py
hiargparse/file_protocols/dict_writers/toml_writer.py
hiargparse/file_protocols/dict_writers/yaml_writer.py
hiargparse/hierarchy/__init__.py
hiargparse/hierarchy/format_parent_names.py
hiargparse/hierarchy/hierarchy.py
hiargparse/miscs/__init__.py
hiargparse/miscs/dirty_accesses.py
hiargparse/miscs/if_none_then.py
hiargparse-0.2.2.dist-info/METADATA
hiargparse-0.2.2.dist-info/RECORD
hiargparse-0.2.2.dist-info/WHEEL
hiargparse-0.2.2.dist-info/top_level.txt
