Metadata-Version: 2.1
Name: hiargparse
Version: 0.2.2
Summary: A hierarchical and highly sophisticated variant of argparse.
Home-page: https://github.com/KKawamura1/hiargparse
Author: Keigo Kawamura
Author-email: kkawamura@logos.t.u-tokyo.ac.jp
License: MIT
Project-URL: Source, https://github.com/KKawamura1/hiargparse/
Keywords: arguments argparse hierarchy
Platform: UNKNOWN
Classifier: Development Status :: 4 - Beta
Classifier: Intended Audience :: Developers
Classifier: License :: OSI Approved :: MIT License
Classifier: Programming Language :: Python :: 3
Classifier: Programming Language :: Python :: 3.6
Classifier: Programming Language :: Python :: 3.7
Classifier: Topic :: Software Development :: Libraries :: Python Modules
Requires-Python: ~=3.6
Requires-Dist: typing-extensions (>=3.6.2.1)
Requires-Dist: pyyaml
Requires-Dist: toml
